odoo10_addon_sequence_check_digit-10.0.1.0.0-py2.7-nspkg.pth
odoo/addons/sequence_check_digit/README.rst
odoo/addons/sequence_check_digit/__init__.py
odoo/addons/sequence_check_digit/__manifest__.py
odoo/addons/sequence_check_digit/i18n/es.po
odoo/addons/sequence_check_digit/models/__init__.py
odoo/addons/sequence_check_digit/models/ir_sequence.py
odoo/addons/sequence_check_digit/static/description/icon.png
odoo/addons/sequence_check_digit/tests/__init__.py
odoo/addons/sequence_check_digit/tests/test_check_digit.py
odoo/addons/sequence_check_digit/views/sequence_views.xml
odoo10_addon_sequence_check_digit-10.0.1.0.0.dist-info/DESCRIPTION.rst
odoo10_addon_sequence_check_digit-10.0.1.0.0.dist-info/METADATA
odoo10_addon_sequence_check_digit-10.0.1.0.0.dist-info/RECORD
odoo10_addon_sequence_check_digit-10.0.1.0.0.dist-info/WHEEL
odoo10_addon_sequence_check_digit-10.0.1.0.0.dist-info/metadata.json
odoo10_addon_sequence_check_digit-10.0.1.0.0.dist-info/namespace_packages.txt
odoo10_addon_sequence_check_digit-10.0.1.0.0.dist-info/top_level.txt
